juxta/__init__.py
juxta-0.0.1.dist-info/METADATA
juxta-0.0.1.dist-info/WHEEL
juxta-0.0.1.dist-info/top_level.txt
juxta-0.0.1.dist-info/RECORD
