Metadata-Version: 2.1
Name: juxta
Version: 0.0.1
Summary: Library facilitating cloud computing
Author: nbreitkopf
Classifier: Programming Language :: Python :: 3
Classifier: Operating System :: OS Independent
Requires-Python: >=3.10
